[
  {
    "title": "Raccoons_L1",
    "link_thumb": "https://live.staticflickr.com/65535/51787738639_4102c4f1ea_o.gif",
    "id_album": "1998705264",
    "total": 20,
    "size_max_detail_page": 1,
    "list_detail": [
      {
        "index_page": 0,
        "link_page": "https://github.com/lmbstudiocontact/mb4_dt_alb_0/raw/main/14132021_dta_1998705264_index_0.json"
      }
    ]
  },
  {
    "title": "Inside Out Cartoon",
    "link_thumb": "https://live.staticflickr.com/65535/51787764720_14df4867f6_o.gif",
    "id_album": "2016762456",
    "total": 4,
    "size_max_detail_page": 1,
    "list_detail": [
      {
        "index_page": 0,
        "link_page": "https://github.com/lmbstudiocontact/mb4_dt_alb_0/raw/main/14132021_dta_2016762456_index_0.json"
      }
    ]
  },
  {
    "title": "Kung Fu Panda_L8",
    "link_thumb": "https://live.staticflickr.com/65535/51787902190_815d459e3f_o.gif",
    "id_album": "1222783557",
    "total": 2,
    "size_max_detail_page": 1,
    "list_detail": [
      {
        "index_page": 0,
        "link_page": "https://github.com/lmbstudiocontact/mb4_dt_alb_0/raw/main/14132021_dta_1222783557_index_0.json"
      }
    ]
  },
  {
    "title": "City_Animation",
    "link_thumb": "https://live.staticflickr.com/65535/51786085872_7fb5e69912_o.gif",
    "id_album": "784273840",
    "total": 1,
    "size_max_detail_page": 1,
    "list_detail": [
      {
        "index_page": 0,
        "link_page": "https://github.com/lmbstudiocontact/mb4_dt_alb_0/raw/main/14132021_dta_784273840_index_0.json"
      }
    ]
  },
  {
    "title": "Music_L9",
    "link_thumb": "https://live.staticflickr.com/65535/51787275318_181a2f4cd9_o.gif",
    "id_album": "908522983",
    "total": 24,
    "size_max_detail_page": 1,
    "list_detail": [
      {
        "index_page": 0,
        "link_page": "https://github.com/lmbstudiocontact/mb4_dt_alb_0/raw/main/14132021_dta_908522983_index_0.json"
      }
    ]
  },
  {
    "title": "Kitty & My Melody_L8",
    "link_thumb": "https://live.staticflickr.com/65535/51786206992_45744b380b_o.gif",
    "id_album": "-378480538",
    "total": 76,
    "size_max_detail_page": 2,
    "list_detail": [
      {
        "index_page": 0,
        "link_page": "https://github.com/lmbstudiocontact/mb4_dt_alb_0/raw/main/14132021_dta_-378480538_index_0.json"
      },
      {
        "index_page": 1,
        "link_page": "https://github.com/lmbstudiocontact/mb4_dt_alb_0/raw/main/14132021_dta_-378480538_index_1.json"
      }
    ]
  },
  {
    "title": "Death Note Anime_L5",
    "link_thumb": "https://live.staticflickr.com/65535/51787803600_f8d3111f7f_o.gif",
    "id_album": "-374116170",
    "total": 8,
    "size_max_detail_page": 1,
    "list_detail": [
      {
        "index_page": 0,
        "link_page": "https://github.com/lmbstudiocontact/mb4_dt_alb_0/raw/main/14132021_dta_-374116170_index_0.json"
      }
    ]
  },
  {
    "title": "Buddhist Terms_L3",
    "link_thumb": "https://live.staticflickr.com/65535/51786915351_b527958e50_o.gif",
    "id_album": "518853930",
    "total": 13,
    "size_max_detail_page": 1,
    "list_detail": [
      {
        "index_page": 0,
        "link_page": "https://github.com/lmbstudiocontact/mb4_dt_alb_0/raw/main/14132021_dta_518853930_index_0.json"
      }
    ]
  },
  {
    "title": "Seven deadly sins Anime_L1",
    "link_thumb": "https://live.staticflickr.com/65535/51787742404_2aac427e8c_o.gif",
    "id_album": "1802210937",
    "total": 43,
    "size_max_detail_page": 1,
    "list_detail": [
      {
        "index_page": 0,
        "link_page": "https://github.com/lmbstudiocontact/mb4_dt_alb_0/raw/main/14132021_dta_1802210937_index_0.json"
      }
    ]
  },
  {
    "title": "Wolf_L1",
    "link_thumb": "https://live.staticflickr.com/65535/51786309357_eddcc77e0d_o.gif",
    "id_album": "-1110849966",
    "total": 5,
    "size_max_detail_page": 1,
    "list_detail": [
      {
        "index_page": 0,
        "link_page": "https://github.com/lmbstudiocontact/mb4_dt_alb_0/raw/main/14132021_dta_-1110849966_index_0.json"
      }
    ]
  },
  {
    "title": "Wolf_L5",
    "link_thumb": "https://live.staticflickr.com/65535/51786311897_ba652df015_o.gif",
    "id_album": "-1110849962",
    "total": 5,
    "size_max_detail_page": 1,
    "list_detail": [
      {
        "index_page": 0,
        "link_page": "https://github.com/lmbstudiocontact/mb4_dt_alb_0/raw/main/14132021_dta_-1110849962_index_0.json"
      }
    ]
  },
  {
    "title": "Couple_L2",
    "link_thumb": "https://live.staticflickr.com/65535/51786098522_53d5c490da_o.gif",
    "id_album": "-888889819",
    "total": 24,
    "size_max_detail_page": 1,
    "list_detail": [
      {
        "index_page": 0,
        "link_page": "https://github.com/lmbstudiocontact/mb4_dt_alb_0/raw/main/14132021_dta_-888889819_index_0.json"
      }
    ]
  },
  {
    "title": "Butterfly_L4",
    "link_thumb": "https://live.staticflickr.com/65535/51786923646_dca5f6427b_o.gif",
    "id_album": "657564372",
    "total": 6,
    "size_max_detail_page": 1,
    "list_detail": [
      {
        "index_page": 0,
        "link_page": "https://github.com/lmbstudiocontact/mb4_dt_alb_0/raw/main/14132021_dta_657564372_index_0.json"
      }
    ]
  },
  {
    "title": "Boku No Hero Academia Anime_L8",
    "link_thumb": "https://live.staticflickr.com/65535/51786102967_c570242194_o.gif",
    "id_album": "197312546",
    "total": 19,
    "size_max_detail_page": 1,
    "list_detail": [
      {
        "index_page": 0,
        "link_page": "https://github.com/lmbstudiocontact/mb4_dt_alb_0/raw/main/14132021_dta_197312546_index_0.json"
      }
    ]
  },
  {
    "title": "Onmyoji_L1",
    "link_thumb": "https://live.staticflickr.com/65535/51787329148_0f2f31d495_o.gif",
    "id_album": "389318913",
    "total": 26,
    "size_max_detail_page": 1,
    "list_detail": [
      {
        "index_page": 0,
        "link_page": "https://github.com/lmbstudiocontact/mb4_dt_alb_0/raw/main/14132021_dta_389318913_index_0.json"
      }
    ]
  },
  {
    "title": "One Piece Anime_L9",
    "link_thumb": "https://live.staticflickr.com/65535/51786271452_05320ab70a_o.gif",
    "id_album": "1351456612",
    "total": 135,
    "size_max_detail_page": 3,
    "list_detail": [
      {
        "index_page": 0,
        "link_page": "https://github.com/lmbstudiocontact/mb4_dt_alb_0/raw/main/14132021_dta_1351456612_index_0.json"
      },
      {
        "index_page": 1,
        "link_page": "https://github.com/lmbstudiocontact/mb4_dt_alb_0/raw/main/14132021_dta_1351456612_index_1.json"
      },
      {
        "index_page": 2,
        "link_page": "https://github.com/lmbstudiocontact/mb4_dt_alb_0/raw/main/14132021_dta_1351456612_index_2.json"
      }
    ]
  },
  {
    "title": "Rio 2_L1",
    "link_thumb": "https://live.staticflickr.com/65535/51787739004_71f0a30d90_o.gif",
    "id_album": "-1210862918",
    "total": 17,
    "size_max_detail_page": 1,
    "list_detail": [
      {
        "index_page": 0,
        "link_page": "https://github.com/lmbstudiocontact/mb4_dt_alb_0/raw/main/14132021_dta_-1210862918_index_0.json"
      }
    ]
  },
  {
    "title": "Kung Fu Panda_L10",
    "link_thumb": "https://live.staticflickr.com/65535/51786189152_a634df8009_o.gif",
    "id_album": "-748415566",
    "total": 2,
    "size_max_detail_page": 1,
    "list_detail": [
      {
        "index_page": 0,
        "link_page": "https://github.com/lmbstudiocontact/mb4_dt_alb_0/raw/main/14132021_dta_-748415566_index_0.json"
      }
    ]
  },
  {
    "title": "Star War_L4",
    "link_thumb": "https://live.staticflickr.com/65535/51787383618_545725840c_o.gif",
    "id_album": "-1637191763",
    "total": 2,
    "size_max_detail_page": 1,
    "list_detail": [
      {
        "index_page": 0,
        "link_page": "https://github.com/lmbstudiocontact/mb4_dt_alb_0/raw/main/14132021_dta_-1637191763_index_0.json"
      }
    ]
  },
  {
    "title": "Ragnarok_L7",
    "link_thumb": "https://live.staticflickr.com/65535/51787984340_aeb670904a_o.gif",
    "id_album": "1601322215",
    "total": 15,
    "size_max_detail_page": 1,
    "list_detail": [
      {
        "index_page": 0,
        "link_page": "https://github.com/lmbstudiocontact/mb4_dt_alb_0/raw/main/14132021_dta_1601322215_index_0.json"
      }
    ]
  },
  {
    "title": "Madagascar Cartoon_L9",
    "link_thumb": "https://live.staticflickr.com/65535/51787014071_6910e9454d_o.gif",
    "id_album": "-2014542382",
    "total": 9,
    "size_max_detail_page": 1,
    "list_detail": [
      {
        "index_page": 0,
        "link_page": "https://github.com/lmbstudiocontact/mb4_dt_alb_0/raw/main/14132021_dta_-2014542382_index_0.json"
      }
    ]
  },
  {
    "title": "Smurf Houses Cartoon_L10",
    "link_thumb": "https://live.staticflickr.com/65535/51786316642_17ba1beba6_o.gif",
    "id_album": "-1513724194",
    "total": 4,
    "size_max_detail_page": 1,
    "list_detail": [
      {
        "index_page": 0,
        "link_page": "https://github.com/lmbstudiocontact/mb4_dt_alb_0/raw/main/14132021_dta_-1513724194_index_0.json"
      }
    ]
  },
  {
    "title": "Donald Duck Cartoon_L3",
    "link_thumb": "https://live.staticflickr.com/65535/51787567309_5372af5597_o.gif",
    "id_album": "-1917621483",
    "total": 4,
    "size_max_detail_page": 1,
    "list_detail": [
      {
        "index_page": 0,
        "link_page": "https://github.com/lmbstudiocontact/mb4_dt_alb_0/raw/main/14132021_dta_-1917621483_index_0.json"
      }
    ]
  },
  {
    "title": "Joker Harley Quinn_L2",
    "link_thumb": "https://live.staticflickr.com/65535/51786175497_42a4759061_o.gif",
    "id_album": "-2022175636",
    "total": 24,
    "size_max_detail_page": 1,
    "list_detail": [
      {
        "index_page": 0,
        "link_page": "https://github.com/lmbstudiocontact/mb4_dt_alb_0/raw/main/14132021_dta_-2022175636_index_0.json"
      }
    ]
  },
  {
    "title": "Couple_L1",
    "link_thumb": "https://live.staticflickr.com/65535/51787538944_88daac6a0e_o.gif",
    "id_album": "-888889820",
    "total": 24,
    "size_max_detail_page": 1,
    "list_detail": [
      {
        "index_page": 0,
        "link_page": "https://github.com/lmbstudiocontact/mb4_dt_alb_0/raw/main/14132021_dta_-888889820_index_0.json"
      }
    ]
  },
  {
    "title": "Space",
    "link_thumb": "https://live.staticflickr.com/65535/51787143183_a94c635f24_o.gif",
    "id_album": "80085222",
    "total": 62,
    "size_max_detail_page": 2,
    "list_detail": [
      {
        "index_page": 0,
        "link_page": "https://github.com/lmbstudiocontact/mb4_dt_alb_0/raw/main/14132021_dta_80085222_index_0.json"
      },
      {
        "index_page": 1,
        "link_page": "https://github.com/lmbstudiocontact/mb4_dt_alb_0/raw/main/14132021_dta_80085222_index_1.json"
      }
    ]
  },
  {
    "title": "One Punch Man Anime_L3",
    "link_thumb": "https://live.staticflickr.com/65535/51787320258_57dd5607a3_o.gif",
    "id_album": "-1626855612",
    "total": 2,
    "size_max_detail_page": 1,
    "list_detail": [
      {
        "index_page": 0,
        "link_page": "https://github.com/lmbstudiocontact/mb4_dt_alb_0/raw/main/14132021_dta_-1626855612_index_0.json"
      }
    ]
  },
  {
    "title": "Boku No Hero Academia Anime_L5",
    "link_thumb": "https://live.staticflickr.com/65535/51787544334_fc03cb49fd_o.gif",
    "id_album": "197312543",
    "total": 19,
    "size_max_detail_page": 1,
    "list_detail": [
      {
        "index_page": 0,
        "link_page": "https://github.com/lmbstudiocontact/mb4_dt_alb_0/raw/main/14132021_dta_197312543_index_0.json"
      }
    ]
  },
  {
    "title": "Language Hungarian",
    "link_thumb": "https://live.staticflickr.com/65535/51787765965_a44fc6489b_o.gif",
    "id_album": "-1762931209",
    "total": 37,
    "size_max_detail_page": 1,
    "list_detail": [
      {
        "index_page": 0,
        "link_page": "https://github.com/lmbstudiocontact/mb4_dt_alb_0/raw/main/14132021_dta_-1762931209_index_0.json"
      }
    ]
  },
  {
    "title": "Plants Vs Zombies_L10",
    "link_thumb": "https://live.staticflickr.com/65535/51787070016_499775d41d_o.gif",
    "id_album": "-1280428562",
    "total": 24,
    "size_max_detail_page": 1,
    "list_detail": [
      {
        "index_page": 0,
        "link_page": "https://github.com/lmbstudiocontact/mb4_dt_alb_0/raw/main/14132021_dta_-1280428562_index_0.json"
      }
    ]
  },
  {
    "title": "One Punch Man Anime_L5",
    "link_thumb": "https://live.staticflickr.com/65535/51787069371_bd2aff738f_o.gif",
    "id_album": "-1626855610",
    "total": 2,
    "size_max_detail_page": 1,
    "list_detail": [
      {
        "index_page": 0,
        "link_page": "https://github.com/lmbstudiocontact/mb4_dt_alb_0/raw/main/14132021_dta_-1626855610_index_0.json"
      }
    ]
  },
  {
    "title": "Animal Art_L2",
    "link_thumb": "https://live.staticflickr.com/65535/51787538139_10a052e355_o.gif",
    "id_album": "97007462",
    "total": 7,
    "size_max_detail_page": 1,
    "list_detail": [
      {
        "index_page": 0,
        "link_page": "https://github.com/lmbstudiocontact/mb4_dt_alb_0/raw/main/14132021_dta_97007462_index_0.json"
      }
    ]
  },
  {
    "title": "Kung Fu Panda_L1",
    "link_thumb": "https://live.staticflickr.com/65535/51787007321_227b411e5a_o.gif",
    "id_album": "1222783550",
    "total": 2,
    "size_max_detail_page": 1,
    "list_detail": [
      {
        "index_page": 0,
        "link_page": "https://github.com/lmbstudiocontact/mb4_dt_alb_0/raw/main/14132021_dta_1222783550_index_0.json"
      }
    ]
  },
  {
    "title": "Buddhist Terms_L5",
    "link_thumb": "https://live.staticflickr.com/65535/51786913026_51d72b2f4f_o.gif",
    "id_album": "518853932",
    "total": 13,
    "size_max_detail_page": 1,
    "list_detail": [
      {
        "index_page": 0,
        "link_page": "https://github.com/lmbstudiocontact/mb4_dt_alb_0/raw/main/14132021_dta_518853932_index_0.json"
      }
    ]
  },
  {
    "title": "Horror Art_L4",
    "link_thumb": "https://live.staticflickr.com/65535/51786170742_11a4f7cc85_o.gif",
    "id_album": "529377274",
    "total": 41,
    "size_max_detail_page": 1,
    "list_detail": [
      {
        "index_page": 0,
        "link_page": "https://github.com/lmbstudiocontact/mb4_dt_alb_0/raw/main/14132021_dta_529377274_index_0.json"
      }
    ]
  },
  {
    "title": "Toy Story Footloose Cartoon",
    "link_thumb": "https://live.staticflickr.com/65535/51787509434_81c717949d_o.gif",
    "id_album": "1776510609",
    "total": 9,
    "size_max_detail_page": 1,
    "list_detail": [
      {
        "index_page": 0,
        "link_page": "https://github.com/lmbstudiocontact/mb4_dt_alb_0/raw/main/14132021_dta_1776510609_index_0.json"
      }
    ]
  },
  {
    "title": "Death Note Anime_L6",
    "link_thumb": "https://live.staticflickr.com/65535/51787189768_f1b28d4833_o.gif",
    "id_album": "-374116169",
    "total": 8,
    "size_max_detail_page": 1,
    "list_detail": [
      {
        "index_page": 0,
        "link_page": "https://github.com/lmbstudiocontact/mb4_dt_alb_0/raw/main/14132021_dta_-374116169_index_0.json"
      }
    ]
  },
  {
    "title": "One Punch Man Anime_L7",
    "link_thumb": "https://live.staticflickr.com/65535/51787941670_ff1cbf6d2b_o.gif",
    "id_album": "-1626855608",
    "total": 2,
    "size_max_detail_page": 1,
    "list_detail": [
      {
        "index_page": 0,
        "link_page": "https://github.com/lmbstudiocontact/mb4_dt_alb_0/raw/main/14132021_dta_-1626855608_index_0.json"
      }
    ]
  },
  {
    "title": "Smurf Houses Cartoon_L4",
    "link_thumb": "https://live.staticflickr.com/65535/51787385853_e4c423b290_o.gif",
    "id_album": "228264853",
    "total": 4,
    "size_max_detail_page": 1,
    "list_detail": [
      {
        "index_page": 0,
        "link_page": "https://github.com/lmbstudiocontact/mb4_dt_alb_0/raw/main/14132021_dta_228264853_index_0.json"
      }
    ]
  },
  {
    "title": "Couple_L3",
    "link_thumb": "https://live.staticflickr.com/65535/51786904131_28c71a3847_o.gif",
    "id_album": "-888889818",
    "total": 24,
    "size_max_detail_page": 1,
    "list_detail": [
      {
        "index_page": 0,
        "link_page": "https://github.com/lmbstudiocontact/mb4_dt_alb_0/raw/main/14132021_dta_-888889818_index_0.json"
      }
    ]
  },
  {
    "title": "Couple_L7",
    "link_thumb": "https://live.staticflickr.com/65535/51786920606_fa5537aaba_o.gif",
    "id_album": "-888889814",
    "total": 24,
    "size_max_detail_page": 1,
    "list_detail": [
      {
        "index_page": 0,
        "link_page": "https://github.com/lmbstudiocontact/mb4_dt_alb_0/raw/main/14132021_dta_-888889814_index_0.json"
      }
    ]
  },
  {
    "title": "Lilo & Stitch Cartoon_L7",
    "link_thumb": "https://live.staticflickr.com/65535/51787276098_b78a09a093_o.gif",
    "id_album": "685543665",
    "total": 30,
    "size_max_detail_page": 1,
    "list_detail": [
      {
        "index_page": 0,
        "link_page": "https://github.com/lmbstudiocontact/mb4_dt_alb_0/raw/main/14132021_dta_685543665_index_0.json"
      }
    ]
  },
  {
    "title": "Halloween Ghost Witch_L10",
    "link_thumb": "https://live.staticflickr.com/65535/51787850950_cffd47f597_o.gif",
    "id_album": "-1690866577",
    "total": 49,
    "size_max_detail_page": 1,
    "list_detail": [
      {
        "index_page": 0,
        "link_page": "https://github.com/lmbstudiocontact/mb4_dt_alb_0/raw/main/14132021_dta_-1690866577_index_0.json"
      }
    ]
  },
  {
    "title": "Music_L6",
    "link_thumb": "https://live.staticflickr.com/65535/51787275388_86928b54ee_o.gif",
    "id_album": "908522980",
    "total": 24,
    "size_max_detail_page": 1,
    "list_detail": [
      {
        "index_page": 0,
        "link_page": "https://github.com/lmbstudiocontact/mb4_dt_alb_0/raw/main/14132021_dta_908522980_index_0.json"
      }
    ]
  },
  {
    "title": "Raccoons_L10",
    "link_thumb": "https://live.staticflickr.com/65535/51787108761_3c35137c2c_o.gif",
    "id_album": "1830321088",
    "total": 20,
    "size_max_detail_page": 1,
    "list_detail": [
      {
        "index_page": 0,
        "link_page": "https://github.com/lmbstudiocontact/mb4_dt_alb_0/raw/main/14132021_dta_1830321088_index_0.json"
      }
    ]
  },
  {
    "title": "Seven deadly sins Anime_L2",
    "link_thumb": "https://live.staticflickr.com/65535/51787988460_f529608ab2_o.gif",
    "id_album": "1802210938",
    "total": 43,
    "size_max_detail_page": 1,
    "list_detail": [
      {
        "index_page": 0,
        "link_page": "https://github.com/lmbstudiocontact/mb4_dt_alb_0/raw/main/14132021_dta_1802210938_index_0.json"
      }
    ]
  },
  {
    "title": "Ghibli Anime_L9",
    "link_thumb": "https://live.staticflickr.com/65535/51787864190_60394d9212_o.gif",
    "id_album": "-749595039",
    "total": 17,
    "size_max_detail_page": 1,
    "list_detail": [
      {
        "index_page": 0,
        "link_page": "https://github.com/lmbstudiocontact/mb4_dt_alb_0/raw/main/14132021_dta_-749595039_index_0.json"
      }
    ]
  },
  {
    "title": "Language Indonesian_Animation",
    "link_thumb": "https://live.staticflickr.com/65535/51786075567_f9ed2c3b68_o.gif",
    "id_album": "1749121239",
    "total": 6,
    "size_max_detail_page": 1,
    "list_detail": [
      {
        "index_page": 0,
        "link_page": "https://github.com/lmbstudiocontact/mb4_dt_alb_0/raw/main/14132021_dta_1749121239_index_0.json"
      }
    ]
  },
  {
    "title": "Dragon Ball Anime_L10",
    "link_thumb": "https://live.staticflickr.com/65535/51786948466_e0ebb0b215_o.gif",
    "id_album": "-1838158388",
    "total": 60,
    "size_max_detail_page": 2,
    "list_detail": [
      {
        "index_page": 0,
        "link_page": "https://github.com/lmbstudiocontact/mb4_dt_alb_0/raw/main/14132021_dta_-1838158388_index_0.json"
      },
      {
        "index_page": 1,
        "link_page": "https://github.com/lmbstudiocontact/mb4_dt_alb_0/raw/main/14132021_dta_-1838158388_index_1.json"
      }
    ]
  },
  {
    "title": "Lilo & Stitch Cartoon_L2",
    "link_thumb": "https://live.staticflickr.com/65535/51787649304_2b7943bddf_o.gif",
    "id_album": "685543660",
    "total": 30,
    "size_max_detail_page": 1,
    "list_detail": [
      {
        "index_page": 0,
        "link_page": "https://github.com/lmbstudiocontact/mb4_dt_alb_0/raw/main/14132021_dta_685543660_index_0.json"
      }
    ]
  }
]