[
  {
    "title": "How to Train Your Dragon Cartoon",
    "link_thumb": "https://live.staticflickr.com/65535/51670514527_b64a73655f_o.gif",
    "id_album": "-1112647647",
    "total": 7,
    "size_max_detail_page": 1,
    "list_detail": [
      {
        "index_page": 0,
        "link_page": "https://github.com/lmbstudiocontact/mb4_dt_alb_0/raw/main/14132021_dta_-1112647647_index_0.json"
      }
    ]
  },
  {
    "title": "One Punch Man Anime_L2",
    "link_thumb": "https://live.staticflickr.com/65535/51685802638_c22bdf2d20_o.gif",
    "id_album": "-1626855613",
    "total": 2,
    "size_max_detail_page": 1,
    "list_detail": [
      {
        "index_page": 0,
        "link_page": "https://github.com/lmbstudiocontact/mb4_dt_alb_0/raw/main/14132021_dta_-1626855613_index_0.json"
      }
    ]
  },
  {
    "title": "Moana Cartoon_L7",
    "link_thumb": "https://live.staticflickr.com/65535/51682514395_85013215b3_o.gif",
    "id_album": "-2101867510",
    "total": 13,
    "size_max_detail_page": 1,
    "list_detail": [
      {
        "index_page": 0,
        "link_page": "https://github.com/lmbstudiocontact/mb4_dt_alb_0/raw/main/14132021_dta_-2101867510_index_0.json"
      }
    ]
  },
  {
    "title": "Madagascar Cartoon_L6",
    "link_thumb": "https://live.staticflickr.com/65535/51682061445_981662bfd9_o.gif",
    "id_album": "-2014542385",
    "total": 9,
    "size_max_detail_page": 1,
    "list_detail": [
      {
        "index_page": 0,
        "link_page": "https://github.com/lmbstudiocontact/mb4_dt_alb_0/raw/main/14132021_dta_-2014542385_index_0.json"
      }
    ]
  },
  {
    "title": "Rio 2_L1",
    "link_thumb": "https://live.staticflickr.com/65535/51688179493_86d3fdf934_o.gif",
    "id_album": "-1210862918",
    "total": 17,
    "size_max_detail_page": 1,
    "list_detail": [
      {
        "index_page": 0,
        "link_page": "https://github.com/lmbstudiocontact/mb4_dt_alb_0/raw/main/14132021_dta_-1210862918_index_0.json"
      }
    ]
  },
  {
    "title": "Angry Birds_L2",
    "link_thumb": "https://live.staticflickr.com/65535/51673456385_8a8628cbb8_o.gif",
    "id_album": "2112729290",
    "total": 26,
    "size_max_detail_page": 1,
    "list_detail": [
      {
        "index_page": 0,
        "link_page": "https://github.com/lmbstudiocontact/mb4_dt_alb_0/raw/main/14132021_dta_2112729290_index_0.json"
      }
    ]
  },
  {
    "title": "Panda Art_L5",
    "link_thumb": "https://live.staticflickr.com/65535/51686462904_a11584b9f9_o.gif",
    "id_album": "586574347",
    "total": 5,
    "size_max_detail_page": 1,
    "list_detail": [
      {
        "index_page": 0,
        "link_page": "https://github.com/lmbstudiocontact/mb4_dt_alb_0/raw/main/14132021_dta_586574347_index_0.json"
      }
    ]
  },
  {
    "title": "Shiv_L1",
    "link_thumb": "https://live.staticflickr.com/65535/51689388745_a9198d2906_o.gif",
    "id_album": "-568595358",
    "total": 32,
    "size_max_detail_page": 1,
    "list_detail": [
      {
        "index_page": 0,
        "link_page": "https://github.com/lmbstudiocontact/mb4_dt_alb_0/raw/main/14132021_dta_-568595358_index_0.json"
      }
    ]
  },
  {
    "title": "Mario Game Cartoon_Animation",
    "link_thumb": "https://live.staticflickr.com/65535/51671534158_a82b35a0e3_o.gif",
    "id_album": "887000033",
    "total": 8,
    "size_max_detail_page": 1,
    "list_detail": [
      {
        "index_page": 0,
        "link_page": "https://github.com/lmbstudiocontact/mb4_dt_alb_0/raw/main/14132021_dta_887000033_index_0.json"
      }
    ]
  },
  {
    "title": "Moana Cartoon_L5",
    "link_thumb": "https://live.staticflickr.com/65535/51682469345_8ffe6a493b_o.gif",
    "id_album": "-2101867512",
    "total": 13,
    "size_max_detail_page": 1,
    "list_detail": [
      {
        "index_page": 0,
        "link_page": "https://github.com/lmbstudiocontact/mb4_dt_alb_0/raw/main/14132021_dta_-2101867512_index_0.json"
      }
    ]
  }
]