[
  {
    "title": "Angry Birds_L1",
    "link_thumb": "https://live.staticflickr.com/65535/51786894641_cbc6240854_o.gif",
    "id_album": "2112729289",
    "total": 26,
    "size_max_detail_page": 1,
    "list_detail": [
      {
        "index_page": 0,
        "link_page": "https://github.com/lmbstudiocontact/mb4_dt_alb_0/raw/main/14132021_dta_2112729289_index_0.json"
      }
    ]
  },
  {
    "title": "Death Note Anime_L10",
    "link_thumb": "https://live.staticflickr.com/65535/51786118357_f472d087fc_o.gif",
    "id_album": "1287300542",
    "total": 8,
    "size_max_detail_page": 1,
    "list_detail": [
      {
        "index_page": 0,
        "link_page": "https://github.com/lmbstudiocontact/mb4_dt_alb_0/raw/main/14132021_dta_1287300542_index_0.json"
      }
    ]
  },
  {
    "title": "Cute Art_L5",
    "link_thumb": "https://live.staticflickr.com/65535/51787529659_02fbf0f714_o.gif",
    "id_album": "-629963486",
    "total": 76,
    "size_max_detail_page": 2,
    "list_detail": [
      {
        "index_page": 0,
        "link_page": "https://github.com/lmbstudiocontact/mb4_dt_alb_0/raw/main/14132021_dta_-629963486_index_0.json"
      },
      {
        "index_page": 1,
        "link_page": "https://github.com/lmbstudiocontact/mb4_dt_alb_0/raw/main/14132021_dta_-629963486_index_1.json"
      }
    ]
  },
  {
    "title": "Seven deadly sins Anime_L9",
    "link_thumb": "https://live.staticflickr.com/65535/51787770904_6f5b135035_o.gif",
    "id_album": "1802210945",
    "total": 43,
    "size_max_detail_page": 1,
    "list_detail": [
      {
        "index_page": 0,
        "link_page": "https://github.com/lmbstudiocontact/mb4_dt_alb_0/raw/main/14132021_dta_1802210945_index_0.json"
      }
    ]
  },
  {
    "title": "Onmyoji_L10",
    "link_thumb": "https://live.staticflickr.com/65535/51787318423_ff8ff7d1e8_o.gif",
    "id_album": "-816015537",
    "total": 26,
    "size_max_detail_page": 1,
    "list_detail": [
      {
        "index_page": 0,
        "link_page": "https://github.com/lmbstudiocontact/mb4_dt_alb_0/raw/main/14132021_dta_-816015537_index_0.json"
      }
    ]
  },
  {
    "title": "Death Note Anime_L2",
    "link_thumb": "https://live.staticflickr.com/65535/51786939441_657788e001_o.gif",
    "id_album": "-374116173",
    "total": 8,
    "size_max_detail_page": 1,
    "list_detail": [
      {
        "index_page": 0,
        "link_page": "https://github.com/lmbstudiocontact/mb4_dt_alb_0/raw/main/14132021_dta_-374116173_index_0.json"
      }
    ]
  },
  {
    "title": "Monsters University Cartoon_Animation",
    "link_thumb": "https://live.staticflickr.com/65535/51787509164_6c4e9c2ce8_o.gif",
    "id_album": "-1611324024",
    "total": 1,
    "size_max_detail_page": 1,
    "list_detail": [
      {
        "index_page": 0,
        "link_page": "https://github.com/lmbstudiocontact/mb4_dt_alb_0/raw/main/14132021_dta_-1611324024_index_0.json"
      }
    ]
  },
  {
    "title": "Fox Art_L7",
    "link_thumb": "https://live.staticflickr.com/65535/51787583944_4ce03aac4f_o.gif",
    "id_album": "-646110856",
    "total": 7,
    "size_max_detail_page": 1,
    "list_detail": [
      {
        "index_page": 0,
        "link_page": "https://github.com/lmbstudiocontact/mb4_dt_alb_0/raw/main/14132021_dta_-646110856_index_0.json"
      }
    ]
  },
  {
    "title": "Kitty & My Melody_L1",
    "link_thumb": "https://live.staticflickr.com/65535/51786203482_195a5c4f42_o.gif",
    "id_album": "-378480545",
    "total": 76,
    "size_max_detail_page": 2,
    "list_detail": [
      {
        "index_page": 0,
        "link_page": "https://github.com/lmbstudiocontact/mb4_dt_alb_0/raw/main/14132021_dta_-378480545_index_0.json"
      },
      {
        "index_page": 1,
        "link_page": "https://github.com/lmbstudiocontact/mb4_dt_alb_0/raw/main/14132021_dta_-378480545_index_1.json"
      }
    ]
  },
  {
    "title": "Nature",
    "link_thumb": "https://live.staticflickr.com/65535/51787769340_6898942ab1_o.gif",
    "id_album": "-1968740153",
    "total": 66,
    "size_max_detail_page": 2,
    "list_detail": [
      {
        "index_page": 0,
        "link_page": "https://github.com/lmbstudiocontact/mb4_dt_alb_0/raw/main/14132021_dta_-1968740153_index_0.json"
      },
      {
        "index_page": 1,
        "link_page": "https://github.com/lmbstudiocontact/mb4_dt_alb_0/raw/main/14132021_dta_-1968740153_index_1.json"
      }
    ]
  },
  {
    "title": "Shiv_L2",
    "link_thumb": "https://live.staticflickr.com/65535/51788007965_c954567705_o.gif",
    "id_album": "-568595357",
    "total": 32,
    "size_max_detail_page": 1,
    "list_detail": [
      {
        "index_page": 0,
        "link_page": "https://github.com/lmbstudiocontact/mb4_dt_alb_0/raw/main/14132021_dta_-568595357_index_0.json"
      }
    ]
  },
  {
    "title": "Rio 2_L9",
    "link_thumb": "https://live.staticflickr.com/65535/51787997260_ecc6eb0ac5_o.gif",
    "id_album": "-1210862910",
    "total": 17,
    "size_max_detail_page": 1,
    "list_detail": [
      {
        "index_page": 0,
        "link_page": "https://github.com/lmbstudiocontact/mb4_dt_alb_0/raw/main/14132021_dta_-1210862910_index_0.json"
      }
    ]
  },
  {
    "title": "Music_L8",
    "link_thumb": "https://live.staticflickr.com/65535/51786195617_af20d035f2_o.gif",
    "id_album": "908522982",
    "total": 24,
    "size_max_detail_page": 1,
    "list_detail": [
      {
        "index_page": 0,
        "link_page": "https://github.com/lmbstudiocontact/mb4_dt_alb_0/raw/main/14132021_dta_908522982_index_0.json"
      }
    ]
  },
  {
    "title": "Naruto Anime_L8",
    "link_thumb": "https://live.staticflickr.com/65535/51787673649_bff6fcba35_o.gif",
    "id_album": "1894397990",
    "total": 37,
    "size_max_detail_page": 1,
    "list_detail": [
      {
        "index_page": 0,
        "link_page": "https://github.com/lmbstudiocontact/mb4_dt_alb_0/raw/main/14132021_dta_1894397990_index_0.json"
      }
    ]
  },
  {
    "title": "Music_L9",
    "link_thumb": "https://live.staticflickr.com/65535/51787275318_181a2f4cd9_o.gif",
    "id_album": "908522983",
    "total": 24,
    "size_max_detail_page": 1,
    "list_detail": [
      {
        "index_page": 0,
        "link_page": "https://github.com/lmbstudiocontact/mb4_dt_alb_0/raw/main/14132021_dta_908522983_index_0.json"
      }
    ]
  },
  {
    "title": "Onmyoji_L4",
    "link_thumb": "https://live.staticflickr.com/65535/51787963530_0d9e49dc1a_o.gif",
    "id_album": "389318916",
    "total": 26,
    "size_max_detail_page": 1,
    "list_detail": [
      {
        "index_page": 0,
        "link_page": "https://github.com/lmbstudiocontact/mb4_dt_alb_0/raw/main/14132021_dta_389318916_index_0.json"
      }
    ]
  },
  {
    "title": "Simpsons Cartoon_L3",
    "link_thumb": "https://live.staticflickr.com/65535/51787147396_14c9361a43_o.gif",
    "id_album": "1276946590",
    "total": 8,
    "size_max_detail_page": 1,
    "list_detail": [
      {
        "index_page": 0,
        "link_page": "https://github.com/lmbstudiocontact/mb4_dt_alb_0/raw/main/14132021_dta_1276946590_index_0.json"
      }
    ]
  },
  {
    "title": "Animals_Animation",
    "link_thumb": "https://live.staticflickr.com/65535/51786898156_23cd3769a3_o.gif",
    "id_album": "1357766396",
    "total": 13,
    "size_max_detail_page": 1,
    "list_detail": [
      {
        "index_page": 0,
        "link_page": "https://github.com/lmbstudiocontact/mb4_dt_alb_0/raw/main/14132021_dta_1357766396_index_0.json"
      }
    ]
  },
  {
    "title": "Rio 2_L5",
    "link_thumb": "https://live.staticflickr.com/65535/51787111411_8345fa321e_o.gif",
    "id_album": "-1210862914",
    "total": 17,
    "size_max_detail_page": 1,
    "list_detail": [
      {
        "index_page": 0,
        "link_page": "https://github.com/lmbstudiocontact/mb4_dt_alb_0/raw/main/14132021_dta_-1210862914_index_0.json"
      }
    ]
  },
  {
    "title": "Joker Harley Quinn_L1",
    "link_thumb": "https://live.staticflickr.com/65535/51786159672_6734d1180a_o.gif",
    "id_album": "-2022175637",
    "total": 24,
    "size_max_detail_page": 1,
    "list_detail": [
      {
        "index_page": 0,
        "link_page": "https://github.com/lmbstudiocontact/mb4_dt_alb_0/raw/main/14132021_dta_-2022175637_index_0.json"
      }
    ]
  },
  {
    "title": "Language Italian_Animation",
    "link_thumb": "https://live.staticflickr.com/65535/51787765295_95b39933be_o.gif",
    "id_album": "-1794846947",
    "total": 6,
    "size_max_detail_page": 1,
    "list_detail": [
      {
        "index_page": 0,
        "link_page": "https://github.com/lmbstudiocontact/mb4_dt_alb_0/raw/main/14132021_dta_-1794846947_index_0.json"
      }
    ]
  },
  {
    "title": "Ratatouille Cartoon_L1",
    "link_thumb": "https://live.staticflickr.com/65535/51787745319_dbefc3d026_o.gif",
    "id_album": "1746345500",
    "total": 5,
    "size_max_detail_page": 1,
    "list_detail": [
      {
        "index_page": 0,
        "link_page": "https://github.com/lmbstudiocontact/mb4_dt_alb_0/raw/main/14132021_dta_1746345500_index_0.json"
      }
    ]
  },
  {
    "title": "Mickey Cartoon_L2",
    "link_thumb": "https://live.staticflickr.com/65535/51786210862_8f751ed132_o.gif",
    "id_album": "1680949823",
    "total": 22,
    "size_max_detail_page": 1,
    "list_detail": [
      {
        "index_page": 0,
        "link_page": "https://github.com/lmbstudiocontact/mb4_dt_alb_0/raw/main/14132021_dta_1680949823_index_0.json"
      }
    ]
  },
  {
    "title": "Donald Duck Cartoon_L8",
    "link_thumb": "https://live.staticflickr.com/65535/51787565379_ed2c82205c_o.gif",
    "id_album": "-1917621478",
    "total": 4,
    "size_max_detail_page": 1,
    "list_detail": [
      {
        "index_page": 0,
        "link_page": "https://github.com/lmbstudiocontact/mb4_dt_alb_0/raw/main/14132021_dta_-1917621478_index_0.json"
      }
    ]
  },
  {
    "title": "Music_L3",
    "link_thumb": "https://live.staticflickr.com/65535/51787648184_572488813f_o.gif",
    "id_album": "908522977",
    "total": 24,
    "size_max_detail_page": 1,
    "list_detail": [
      {
        "index_page": 0,
        "link_page": "https://github.com/lmbstudiocontact/mb4_dt_alb_0/raw/main/14132021_dta_908522977_index_0.json"
      }
    ]
  },
  {
    "title": "Dragon Art_L3",
    "link_thumb": "https://live.staticflickr.com/65535/51786943826_9f4d460e59_o.gif",
    "id_album": "2059014000",
    "total": 13,
    "size_max_detail_page": 1,
    "list_detail": [
      {
        "index_page": 0,
        "link_page": "https://github.com/lmbstudiocontact/mb4_dt_alb_0/raw/main/14132021_dta_2059014000_index_0.json"
      }
    ]
  },
  {
    "title": "Angry Birds_L4",
    "link_thumb": "https://live.staticflickr.com/65535/51786917196_d880acbd1c_o.gif",
    "id_album": "2112729292",
    "total": 26,
    "size_max_detail_page": 1,
    "list_detail": [
      {
        "index_page": 0,
        "link_page": "https://github.com/lmbstudiocontact/mb4_dt_alb_0/raw/main/14132021_dta_2112729292_index_0.json"
      }
    ]
  },
  {
    "title": "Football_L2",
    "link_thumb": "https://live.staticflickr.com/65535/51787840910_a799efe5b2_o.gif",
    "id_album": "-371026088",
    "total": 49,
    "size_max_detail_page": 1,
    "list_detail": [
      {
        "index_page": 0,
        "link_page": "https://github.com/lmbstudiocontact/mb4_dt_alb_0/raw/main/14132021_dta_-371026088_index_0.json"
      }
    ]
  },
  {
    "title": "Shiv_L6",
    "link_thumb": "https://live.staticflickr.com/65535/51787144651_d17b300553_o.gif",
    "id_album": "-568595353",
    "total": 32,
    "size_max_detail_page": 1,
    "list_detail": [
      {
        "index_page": 0,
        "link_page": "https://github.com/lmbstudiocontact/mb4_dt_alb_0/raw/main/14132021_dta_-568595353_index_0.json"
      }
    ]
  },
  {
    "title": "Finding Dory, Finding Nemo Cartoon",
    "link_thumb": "https://live.staticflickr.com/65535/51786877431_f6a310c563_o.gif",
    "id_album": "1136446587",
    "total": 1,
    "size_max_detail_page": 1,
    "list_detail": [
      {
        "index_page": 0,
        "link_page": "https://github.com/lmbstudiocontact/mb4_dt_alb_0/raw/main/14132021_dta_1136446587_index_0.json"
      }
    ]
  },
  {
    "title": "Mario Game Cartoon",
    "link_thumb": "https://live.staticflickr.com/65535/51786893736_d8932517d5_o.gif",
    "id_album": "1297637628",
    "total": 7,
    "size_max_detail_page": 1,
    "list_detail": [
      {
        "index_page": 0,
        "link_page": "https://github.com/lmbstudiocontact/mb4_dt_alb_0/raw/main/14132021_dta_1297637628_index_0.json"
      }
    ]
  },
  {
    "title": "Couple_L4",
    "link_thumb": "https://live.staticflickr.com/65535/51787168243_1fe7ae16c0_o.gif",
    "id_album": "-888889817",
    "total": 24,
    "size_max_detail_page": 1,
    "list_detail": [
      {
        "index_page": 0,
        "link_page": "https://github.com/lmbstudiocontact/mb4_dt_alb_0/raw/main/14132021_dta_-888889817_index_0.json"
      }
    ]
  },
  {
    "title": "Pokmon Anime_L9",
    "link_thumb": "https://live.staticflickr.com/65535/51787119011_68ea8ca36b_o.gif",
    "id_album": "-555824136",
    "total": 108,
    "size_max_detail_page": 3,
    "list_detail": [
      {
        "index_page": 0,
        "link_page": "https://github.com/lmbstudiocontact/mb4_dt_alb_0/raw/main/14132021_dta_-555824136_index_0.json"
      },
      {
        "index_page": 1,
        "link_page": "https://github.com/lmbstudiocontact/mb4_dt_alb_0/raw/main/14132021_dta_-555824136_index_1.json"
      },
      {
        "index_page": 2,
        "link_page": "https://github.com/lmbstudiocontact/mb4_dt_alb_0/raw/main/14132021_dta_-555824136_index_2.json"
      }
    ]
  },
  {
    "title": "Kung Fu Panda_L7",
    "link_thumb": "https://live.staticflickr.com/65535/51787030861_86acca8cfe_o.gif",
    "id_album": "1222783556",
    "total": 2,
    "size_max_detail_page": 1,
    "list_detail": [
      {
        "index_page": 0,
        "link_page": "https://github.com/lmbstudiocontact/mb4_dt_alb_0/raw/main/14132021_dta_1222783556_index_0.json"
      }
    ]
  },
  {
    "title": "Smurf Houses Cartoon_L5",
    "link_thumb": "https://live.staticflickr.com/65535/51788008465_0dcd84829e_o.gif",
    "id_album": "228264854",
    "total": 4,
    "size_max_detail_page": 1,
    "list_detail": [
      {
        "index_page": 0,
        "link_page": "https://github.com/lmbstudiocontact/mb4_dt_alb_0/raw/main/14132021_dta_228264854_index_0.json"
      }
    ]
  },
  {
    "title": "Other 1_Animation",
    "link_thumb": "https://live.staticflickr.com/65535/51786080627_8e7955a6eb_o.gif",
    "id_album": "-975585370",
    "total": 45,
    "size_max_detail_page": 1,
    "list_detail": [
      {
        "index_page": 0,
        "link_page": "https://github.com/lmbstudiocontact/mb4_dt_alb_0/raw/main/14132021_dta_-975585370_index_0.json"
      }
    ]
  },
  {
    "title": "Butterfly_L4",
    "link_thumb": "https://live.staticflickr.com/65535/51786923646_dca5f6427b_o.gif",
    "id_album": "657564372",
    "total": 6,
    "size_max_detail_page": 1,
    "list_detail": [
      {
        "index_page": 0,
        "link_page": "https://github.com/lmbstudiocontact/mb4_dt_alb_0/raw/main/14132021_dta_657564372_index_0.json"
      }
    ]
  },
  {
    "title": "Language Dutch",
    "link_thumb": "https://live.staticflickr.com/65535/51787146133_d3bf8470bc_o.gif",
    "id_album": "1548992224",
    "total": 37,
    "size_max_detail_page": 1,
    "list_detail": [
      {
        "index_page": 0,
        "link_page": "https://github.com/lmbstudiocontact/mb4_dt_alb_0/raw/main/14132021_dta_1548992224_index_0.json"
      }
    ]
  },
  {
    "title": "Ghibli Anime_L10",
    "link_thumb": "https://live.staticflickr.com/65535/51787214423_848d59d48b_o.gif",
    "id_album": "-1762609929",
    "total": 17,
    "size_max_detail_page": 1,
    "list_detail": [
      {
        "index_page": 0,
        "link_page": "https://github.com/lmbstudiocontact/mb4_dt_alb_0/raw/main/14132021_dta_-1762609929_index_0.json"
      }
    ]
  },
  {
    "title": "Shiv_L7",
    "link_thumb": "https://live.staticflickr.com/65535/51787766874_76f6e5b2ec_o.gif",
    "id_album": "-568595352",
    "total": 32,
    "size_max_detail_page": 1,
    "list_detail": [
      {
        "index_page": 0,
        "link_page": "https://github.com/lmbstudiocontact/mb4_dt_alb_0/raw/main/14132021_dta_-568595352_index_0.json"
      }
    ]
  },
  {
    "title": "City",
    "link_thumb": "https://live.staticflickr.com/65535/51787772240_1c1d088491_o.gif",
    "id_album": "2100619",
    "total": 8,
    "size_max_detail_page": 1,
    "list_detail": [
      {
        "index_page": 0,
        "link_page": "https://github.com/lmbstudiocontact/mb4_dt_alb_0/raw/main/14132021_dta_2100619_index_0.json"
      }
    ]
  },
  {
    "title": "Cute Art_L6",
    "link_thumb": "https://live.staticflickr.com/65535/51787569009_dbb2b00b0b_o.gif",
    "id_album": "-629963485",
    "total": 76,
    "size_max_detail_page": 2,
    "list_detail": [
      {
        "index_page": 0,
        "link_page": "https://github.com/lmbstudiocontact/mb4_dt_alb_0/raw/main/14132021_dta_-629963485_index_0.json"
      },
      {
        "index_page": 1,
        "link_page": "https://github.com/lmbstudiocontact/mb4_dt_alb_0/raw/main/14132021_dta_-629963485_index_1.json"
      }
    ]
  },
  {
    "title": "Anime",
    "link_thumb": "https://live.staticflickr.com/65535/51786898256_173d981aab_o.gif",
    "id_album": "63410260",
    "total": 617,
    "size_max_detail_page": 13,
    "list_detail": [
      {
        "index_page": 0,
        "link_page": "https://github.com/lmbstudiocontact/mb4_dt_alb_0/raw/main/14132021_dta_63410260_index_0.json"
      },
      {
        "index_page": 1,
        "link_page": "https://github.com/lmbstudiocontact/mb4_dt_alb_0/raw/main/14132021_dta_63410260_index_1.json"
      },
      {
        "index_page": 2,
        "link_page": "https://github.com/lmbstudiocontact/mb4_dt_alb_0/raw/main/14132021_dta_63410260_index_2.json"
      },
      {
        "index_page": 3,
        "link_page": "https://github.com/lmbstudiocontact/mb4_dt_alb_0/raw/main/14132021_dta_63410260_index_3.json"
      },
      {
        "index_page": 4,
        "link_page": "https://github.com/lmbstudiocontact/mb4_dt_alb_0/raw/main/14132021_dta_63410260_index_4.json"
      },
      {
        "index_page": 5,
        "link_page": "https://github.com/lmbstudiocontact/mb4_dt_alb_0/raw/main/14132021_dta_63410260_index_5.json"
      },
      {
        "index_page": 6,
        "link_page": "https://github.com/lmbstudiocontact/mb4_dt_alb_0/raw/main/14132021_dta_63410260_index_6.json"
      },
      {
        "index_page": 7,
        "link_page": "https://github.com/lmbstudiocontact/mb4_dt_alb_0/raw/main/14132021_dta_63410260_index_7.json"
      },
      {
        "index_page": 8,
        "link_page": "https://github.com/lmbstudiocontact/mb4_dt_alb_0/raw/main/14132021_dta_63410260_index_8.json"
      },
      {
        "index_page": 9,
        "link_page": "https://github.com/lmbstudiocontact/mb4_dt_alb_0/raw/main/14132021_dta_63410260_index_9.json"
      },
      {
        "index_page": 10,
        "link_page": "https://github.com/lmbstudiocontact/mb4_dt_alb_0/raw/main/14132021_dta_63410260_index_10.json"
      },
      {
        "index_page": 11,
        "link_page": "https://github.com/lmbstudiocontact/mb4_dt_alb_0/raw/main/14132021_dta_63410260_index_11.json"
      },
      {
        "index_page": 12,
        "link_page": "https://github.com/lmbstudiocontact/mb4_dt_alb_0/raw/main/14132021_dta_63410260_index_12.json"
      }
    ]
  },
  {
    "title": "Animal Art_L8",
    "link_thumb": "https://live.staticflickr.com/65535/51786917476_5177963b37_o.gif",
    "id_album": "97007468",
    "total": 7,
    "size_max_detail_page": 1,
    "list_detail": [
      {
        "index_page": 0,
        "link_page": "https://github.com/lmbstudiocontact/mb4_dt_alb_0/raw/main/14132021_dta_97007468_index_0.json"
      }
    ]
  },
  {
    "title": "Star War_L6",
    "link_thumb": "https://live.staticflickr.com/65535/51788005280_29174564ab_o.gif",
    "id_album": "-1637191761",
    "total": 2,
    "size_max_detail_page": 1,
    "list_detail": [
      {
        "index_page": 0,
        "link_page": "https://github.com/lmbstudiocontact/mb4_dt_alb_0/raw/main/14132021_dta_-1637191761_index_0.json"
      }
    ]
  },
  {
    "title": "People",
    "link_thumb": "https://live.staticflickr.com/65535/51787522794_a7db398457_o.gif",
    "id_album": "-1907941713",
    "total": 29,
    "size_max_detail_page": 1,
    "list_detail": [
      {
        "index_page": 0,
        "link_page": "https://github.com/lmbstudiocontact/mb4_dt_alb_0/raw/main/14132021_dta_-1907941713_index_0.json"
      }
    ]
  },
  {
    "title": "Moana Cartoon_L1",
    "link_thumb": "https://live.staticflickr.com/65535/51787899965_b6b2cf28b3_o.gif",
    "id_album": "-2101867516",
    "total": 13,
    "size_max_detail_page": 1,
    "list_detail": [
      {
        "index_page": 0,
        "link_page": "https://github.com/lmbstudiocontact/mb4_dt_alb_0/raw/main/14132021_dta_-2101867516_index_0.json"
      }
    ]
  },
  {
    "title": "Dragon Art_L9",
    "link_thumb": "https://live.staticflickr.com/65535/51787182508_177a48a28e_o.gif",
    "id_album": "2059014006",
    "total": 13,
    "size_max_detail_page": 1,
    "list_detail": [
      {
        "index_page": 0,
        "link_page": "https://github.com/lmbstudiocontact/mb4_dt_alb_0/raw/main/14132021_dta_2059014006_index_0.json"
      }
    ]
  },
  {
    "title": "Seven deadly sins Anime_L1",
    "link_thumb": "https://live.staticflickr.com/65535/51787742404_2aac427e8c_o.gif",
    "id_album": "1802210937",
    "total": 43,
    "size_max_detail_page": 1,
    "list_detail": [
      {
        "index_page": 0,
        "link_page": "https://github.com/lmbstudiocontact/mb4_dt_alb_0/raw/main/14132021_dta_1802210937_index_0.json"
      }
    ]
  },
  {
    "title": "Cute Art_L7",
    "link_thumb": "https://live.staticflickr.com/65535/51786942131_bd3d88d1af_o.gif",
    "id_album": "-629963484",
    "total": 76,
    "size_max_detail_page": 2,
    "list_detail": [
      {
        "index_page": 0,
        "link_page": "https://github.com/lmbstudiocontact/mb4_dt_alb_0/raw/main/14132021_dta_-629963484_index_0.json"
      },
      {
        "index_page": 1,
        "link_page": "https://github.com/lmbstudiocontact/mb4_dt_alb_0/raw/main/14132021_dta_-629963484_index_1.json"
      }
    ]
  }
]